Metadata-Version: 2.1
Name: km-marc
Version: 0.2.2
Summary: Parse and write MARC files
Home-page: https://github.com/KalmeMarq/km-marc
Author: KalmeMarq
License: Copyright (c) 2016 The Python Packaging Authority (PyPA)
Project-URL: Homepage, https://github.com/KalmeMarq/km-marc
Project-URL: Bug Reports, https://github.com/KalmeMarq/km-marc/issues
Project-URL: Source, https://github.com/KalmeMarq/km-marc/
Keywords: marc,setuptools,development
Classifier: Development Status :: 3 - Alpha
Classifier: Intended Audience :: Developers
Classifier: Topic :: Software Development :: Build Tools
Classifier: License :: OSI Approved :: MIT License
Classifier: Programming Language :: Python :: 3
Classifier: Programming Language :: Python :: 3.7
Classifier: Programming Language :: Python :: 3.8
Classifier: Programming Language :: Python :: 3.9
Classifier: Programming Language :: Python :: 3.10
Classifier: Programming Language :: Python :: 3.11
Classifier: Programming Language :: Python :: 3 :: Only
Requires-Python: >=3.7, <4
License-File: LICENSE.txt
Requires-Dist: pyyaml
Provides-Extra: dev
Requires-Dist: check-manifest; extra == "dev"
Provides-Extra: test
Requires-Dist: coverage; extra == "test"
